yoo_telegram/Notifier.py
yoo_telegram/__init__.py
yoo_telegram-0.2.dist-info/LICENSE
yoo_telegram-0.2.dist-info/METADATA
yoo_telegram-0.2.dist-info/WHEEL
yoo_telegram-0.2.dist-info/top_level.txt
yoo_telegram-0.2.dist-info/RECORD
