Metadata-Version: 2.1
Name: yoo-telegram
Version: 0.2
Summary: The bridge between code and your telegram messages.
Author: William Brach
Author-email: <wibrach@gmail.com>
License: UNKNOWN
Keywords: python,telegram,notifications,notifier,bot
Platform: UNKNOWN
Classifier: Intended Audience :: Developers
Classifier: Programming Language :: Python :: 3
Classifier: Operating System :: Unix
Classifier: Operating System :: MacOS :: MacOS X
Classifier: Operating System :: Microsoft :: Windows
License-File: LICENSE
Requires-Dist: requests
